trdicom/__init__.py
trdicom/scp.py
trdicom/scu.py
trdicom/core/__init__.py
trdicom/core/base.py
trdicom/core/scp.py
trdicom/core/scu.py
trdicom-1.0.3.dist-info/licenses/LICENSE
trdicom-1.0.3.dist-info/METADATA
trdicom-1.0.3.dist-info/WHEEL
trdicom-1.0.3.dist-info/top_level.txt
trdicom-1.0.3.dist-info/RECORD
